{"frameRate":24,"name":"luke","version":"5.5","compatibleVersion":"5.5","armature":[{"type":"Armature","frameRate":24,"name":"luke","aabb":{"x":-150,"y":-150,"width":300,"height":300},"bone":[{"name":"luke"}],"slot":[{"displayIndex":8,"name":"luke idle with sheath_1","parent":"luke"}],"skin":[{"slot":[{"name":"luke idle with sheath_1","display":[{"name":"luke idle with sheath_1"},{"name":"luke idle with sheath_2"},{"name":"luke idle with sheath_3"},{"name":"luke wait with sheathe_1"},{"name":"luke wait with sheathe_2"},{"name":"luke wait with sheathe_3"},{"name":"luke wait with sheathe_4"},{"name":"luke wait with sheathe_5"},{"name":"luke cast real_1"},{"name":"luke cast real_2"},{"name":"luke cast real_3"},{"name":"luke cast real_4"},{"name":"luke cast real_5"},{"name":"luke cast real_6"},{"name":"luke cast real_7"},{"name":"luke cast real_8"},{"name":"luke cast real_9"},{"name":"luke cast real_10"},{"name":"luke attack with sheath real_1"},{"name":"luke attack with sheath real_2"},{"name":"luke attack with sheath real_3"},{"name":"luke attack with sheath real_4"},{"name":"luke attack with sheath real_5"},{"name":"luke attack with sheath real_6"},{"name":"luke attack with sheath real_7"},{"name":"luke attack with sheath real_8"},{"name":"luke attack with sheath real_9"},{"name":"luke cast real_11"},{"name":"luke chant_1"},{"name":"luke chant_2"},{"name":"luke chant_3"},{"name":"luke chant_4"},{"name":"luke chant_5"},{"name":"luke chant_6"},{"name":"luke chant_7"},{"name":"luke chant_8"},{"name":"luke idle new_1"},{"name":"luke idle new_2"},{"name":"luke idle new_3"},{"name":"luke idle new_4"},{"name":"luke idle new_5"},{"name":"luke idle new_6"},{"name":"luke idle new_7"},{"name":"luke idle new_8"},{"name":"luke item_1"},{"name":"luke item_2"},{"name":"luke item_3"},{"name":"luke item_4"},{"name":"luke item_5"},{"name":"luke item_6"},{"name":"luke item_7"},{"name":"luke item_8"},{"name":"luke deadWalk 06"}]}]}],"animation":[{"duration":42,"playTimes":0,"name":"idle","slot":[{"name":"luke idle with sheath_1","displayFrame":[{"duration":6,"value":36},{"duration":6,"value":37},{"duration":6,"value":38},{"duration":6,"value":39},{"duration":6,"value":40},{"duration":6,"value":41},{"duration":6,"value":42},{"duration":0,"value":43}]}]},{"duration":24,"playTimes":0,"name":"wait","slot":[{"name":"luke idle with sheath_1","displayFrame":[{"duration":6,"value":5},{"duration":6,"value":6},{"duration":6,"value":7},{"duration":6,"value":6},{"duration":0,"value":5}]}]},{"duration":48,"name":"cast","slot":[{"name":"luke idle with sheath_1","displayFrame":[{"duration":4,"value":8},{"duration":4,"value":9},{"duration":4,"value":10},{"duration":4,"value":11},{"duration":4,"value":12},{"duration":4,"value":13},{"duration":4,"value":15},{"duration":4,"value":16},{"duration":4,"value":17},{"duration":4,"value":27},{"duration":8,"value":17},{"duration":0,"value":27}]}]},{"duration":36,"name":"attack","slot":[{"name":"luke idle with sheath_1","displayFrame":[{"duration":4,"value":18},{"duration":4,"value":19},{"duration":4,"value":20},{"duration":4,"value":21},{"duration":4,"value":22},{"duration":4,"value":23},{"duration":4,"value":24},{"duration":4,"value":25},{"duration":4,"value":26}]}]},{"duration":28,"name":"chant","slot":[{"name":"luke idle with sheath_1","displayFrame":[{"duration":4,"value":28},{"duration":4,"value":29},{"duration":4,"value":30},{"duration":4,"value":31},{"duration":4,"value":32},{"duration":4,"value":33},{"duration":4,"value":34},{"duration":0,"value":35}]}]},{"duration":28,"name":"item","slot":[{"name":"luke idle with sheath_1","displayFrame":[{"duration":4,"value":44},{"duration":4,"value":45},{"duration":4,"value":46},{"duration":4,"value":47},{"duration":4,"value":48},{"duration":4,"value":49},{"duration":4,"value":50},{"duration":0,"value":51}]}]},{"duration":3,"playTimes":0,"name":"dead","slot":[{"name":"luke idle with sheath_1","displayFrame":[{"duration":3,"value":52},{"duration":0,"value":-1}]}]}],"defaultActions":[{"gotoAndPlay":"idle"}]}]}